fw_gear_deid_export/__init__.py
fw_gear_deid_export/container_export.py
fw_gear_deid_export/deid_file.py
fw_gear_deid_export/deid_template.py
fw_gear_deid_export/file_exporter.py
fw_gear_deid_export/metadata_export.py
fw_gear_deid_export/parser.py
fw_gear_deid_export/retry.py
fw_gear_deid_export/retry_utils.py
fw_gear_deid_export/uploader.py
fw_gear_deid_export/var_utils.py
fw_gear_deid_export/assets/dsi_req_jsonschema.json
fw_gear_deid_export/assets/dsi_resp_jsonschema.json
fw_gear_deid_export/assets/root_authority_G3.pem
fw_gear_deid_export-1.9.0.dist-info/METADATA
fw_gear_deid_export-1.9.0.dist-info/WHEEL
fw_gear_deid_export-1.9.0.dist-info/licenses/LICENSE
fw_gear_deid_export-1.9.0.dist-info/RECORD
