Metadata-Version: 2.4
Name: fw-gear-deid-export
Version: 1.9.0
Summary: Utilities for de-identification/anonymization of files within Flywheel
Project-URL: Repository, https://gitlab.com/flywheel-io/scientific-solutions/gears/deid-export
Author-email: "Flywheel, Inc." <support@flywheel.io>
License-Expression: MIT
License-File: LICENSE
Requires-Python: ~=3.12
Requires-Dist: flywheel-gear-toolkit<0.7,>=0.6
Requires-Dist: flywheel-migration[pixel]~=13.10
Requires-Dist: flywheel-sdk~=20.3
Requires-Dist: jinja2~=3.1
Requires-Dist: joblib~=1.5
Requires-Dist: markupsafe<2.1
